{
    "@class": "com.kony.gen.viz.model.component.KVizLabel",
    "DNDConfig": null,
    "_height_": {
        "type": "ref",
        "value": "preferred"
    },
    "_left_": {
        "type": "string",
        "value": "12%"
    },
    "_margin_": [
        0,
        0,
        0,
        0
    ],
    "_padding_": [
        0,
        0,
        0,
        0
    ],
    "_skin_": "s656db9b28be46c59f6db582ec28e58d",
    "_text_": "",
    "_top_": {
        "type": "string",
        "value": "10dp"
    },
    "_width_": {
        "type": "ref",
        "value": "preferred"
    },
    "_wrapping_": 2,
    "android": {
        "textStyle": {
            "letterSpacing": 0,
            "strikeThrough": false
        }
    },
    "canUpdateUI": true,
    "containerweight": 100,
    "contentalignment": 4,
    "desktopweb": {
        "psp": {
            "hoverSkin": "seecb9eb2cbf48949c19601205400ec8"
        }
    },
    "disabledSkins": {},
    "id": "BuildingDark",
    "info": null,
    "ipad": {
        "psp": {
            "wrapping": 2
        }
    },
    "iphone": {
        "psp": {
            "wrapping": 2
        }
    },
    "isvisible": true,
    "kuid": "e34e1c7f48874f9c8299f249610d2278",
    "masterType": 1,
    "name": "kony.ui.Label",
    "parent": "CopyFlexContainer0af1a30f32aeb48",
    "pf": "frmGuestList3",
    "tooltip": "",
    "wType": "Label",
    "zindex": 1
}